paipage/__init__.py
paipage/admin.py
paipage/apps.py
paipage/config.py
paipage/const.py
paipage/jinja2.py
paipage/models.py
paipage/templating.py
paipage/urls.py
paipage/migrations/0001_initial.py
paipage/migrations/0002_auto_20200519_1746.py
paipage/migrations/0003_auto_20200611_1720.py
paipage/migrations/0004_globalsetting_updated_by.py
paipage/migrations/0005_page_other_settings.py
paipage/migrations/__init__.py
paipage/plugins/primary/__init__.py
paipage/plugins/primary/static/_pai-primary-main.css
paipage/plugins/primary/static/adminka.css
paipage/plugins/primary/static/jquery.masonry.min.js
paipage/plugins/primary/static/main.css
paipage/plugins/primary/static/main.js
paipage/plugins/primary/static/paf.js
paipage/plugins/primary/templates/_macros.html
paipage/plugins/primary/templates/am-lo.html
paipage/plugins/primary/templates/am-main.html
paipage/plugins/primary/templates/am-page.html
paipage/plugins/primary/templates/am-plugins.html
paipage/plugins/primary/templates/am-struct.html
paipage/plugins/primary/templates/basic.html
paipage/plugins/primary/templates/lo-pure.html
paipage/plugins/primary/templates/ot-nolang.html
paipage/plugins/primary/templates/ot-output.html
paipage/plugins/primary/templates/pg-pure.html
paipage/plugins/simple/__init__.py
paipage/plugins/simple/static/lo-menu-left.css
paipage/plugins/simple/static/lo-menu-top.css
paipage/plugins/simple/templates/_utils.html
paipage/plugins/simple/templates/lo-menu-left.html
paipage/plugins/simple/templates/lo-menu-top.html
paipage/plugins/simple/templates/pg-cluster.html
paipage/plugins/simple/templates/pg-contents.html
paipage/plugins/simple/templates/pg-usual.html
paipage/views/__init__.py
paipage/views/adminkaMain.py
paipage/views/adminkaPlugins.py
paipage/views/adminkaStruct.py
paipage/views/minor.py
paipage/views/page.py
paipage/views/params.py
paipage/views/special.py
PaiPage-1.0.4.dist-info/LICENSE
PaiPage-1.0.4.dist-info/METADATA
PaiPage-1.0.4.dist-info/WHEEL
PaiPage-1.0.4.dist-info/top_level.txt
PaiPage-1.0.4.dist-info/RECORD
