Metadata-Version: 2.1
Name: PaiPage
Version: 1.0.4
Summary: A simple CMS with languages and themes
Home-page: https://github.com/AivanF/PaiPage
Author: AivanF.
Author-email: projects@aivanf.com
License: UNKNOWN
Platform: UNKNOWN
Classifier: Development Status :: 4 - Beta
Classifier: Programming Language :: Python :: 3
Classifier: Operating System :: OS Independent
Classifier: Environment :: Web Environment
Classifier: Framework :: Django CMS
Classifier: License :: Freely Distributable
License-File: LICENSE
